parade/__init__.py
parade/command/lab.py
parade/command/notebook.py
parade/template/__init__.py
parade/template/workspace/jupyter/__init__.py
parade/template/workspace/jupyter/ipython/__init__.py
parade/template/workspace/jupyter/ipython/profile_parade/__init__.py
parade/template/workspace/jupyter/ipython/profile_parade/startup/00-parade.py
parade/template/workspace/jupyter/ipython/profile_parade/startup/__init__.py
parade/template/workspace/jupyter/kernels/__init__.py
parade/template/workspace/jupyter/kernels/parade/__init__.py
parade/template/workspace/jupyter/kernels/parade/kernel.json
parade/template/workspace/jupyter/kernels/parade/logo-32x32.png
parade/template/workspace/jupyter/kernels/parade/logo-64x64.png
parade/template/workspace/jupyter/notebook/__init__.py
parade_notebook-0.0.2.dist-info/LICENSE
parade_notebook-0.0.2.dist-info/METADATA
parade_notebook-0.0.2.dist-info/WHEEL
parade_notebook-0.0.2.dist-info/top_level.txt
parade_notebook-0.0.2.dist-info/RECORD
