Metadata-Version: 2.1
Name: parade-notebook
Version: 0.0.2
Summary: A notebook module of parade
Home-page: https://github.com/bailaohe/parade-notebook
Author: He Bai
Author-email: bailaohe@gmail.com
License: UNKNOWN
Keywords: parade,feature
Platform: any
Classifier: Development Status :: 4 - Beta
Classifier: Intended Audience :: Developers
Classifier: License :: OSI Approved :: Apache Software License
Classifier: Programming Language :: Python :: 3
Classifier: Topic :: Database
Classifier: Topic :: Software Development :: Libraries :: Python Modules
Classifier: Operating System :: Unix
Classifier: Operating System :: MacOS :: MacOS X
Classifier: Operating System :: Microsoft :: Windows
Classifier: Operating System :: POSIX
Requires-Python: >=3.4
Requires-Dist: parade
Requires-Dist: jupyter
Requires-Dist: nbformat
